HISTORY.rst
LICENSE
MANIFEST.in
README.rst
setup.py
doc/Makefile
doc/api.rst
doc/conf.py
doc/index.rst
doc/make.bat
doc/prerequisites.rst
doc/simpleusage.rst
pykayacim/__init__.py
pykayacim/api.py
pykayacim/constants.py
pykayacim/exceptions.py
pykayacim/ezkayacim.py
pykayacim.egg-info/PKG-INFO
pykayacim.egg-info/SOURCES.txt
pykayacim.egg-info/dependency_links.txt
pykayacim.egg-info/entry_points.txt
pykayacim.egg-info/requires.txt
pykayacim.egg-info/top_level.txt