Metadata-Version: 1.1
Name: pykayacim
Version: 0.1.0
Summary: Send push notifications via im.kayac.com.
Home-page: https://github.com/hamukichi/pykayacim
Author: Hamukichi (Nombiri)
Author-email: hamukichi-dev@outlook.jp
License: MIT License
Keywords: im.kayac.com,notification,Kayac,push,iPhone,Jabbler
Platform: UNKNOWN
Classifier: Programming Language :: Python
Classifier: Programming Language :: Python :: 2.7
Classifier: Programming Language :: Python :: 3
Classifier: Programming Language :: Python :: 3.4
Classifier: License :: OSI Approved :: MIT License
Classifier: Operating System :: OS Independent
Classifier: Development Status :: 4 - Beta
Classifier: Intended Audience :: Developers
Classifier: Topic :: Internet :: WWW/HTTP
Classifier: Topic :: Utilities
Provides: pykayacim
